{"devicePlatform":"","logFolder":"C:\\Katalon Studio\\Deliverable-4\\Reports\\Deliverable-4 Corner\\20180325_195636","runData":{"hostName":"jenni - DESKTOP-C9DGACK","os":"Windows 10 64bit","katalonVersion":"5.3.1.1","browser":"Chrome 65.0.3325.181","hostAddress":"192.168.0.103","sessionId":"ebe69397d19f6e0ca07d1a63548dd16f","seleniumVersion":"3.7.1","proxyInformation":"ProxyInformation{proxyOption\u003dNO_PROXY, proxyServerType\u003dHTTP, password\u003d, proxyServerAddress\u003d, proxyServerPort\u003d0}","platform":"Windows 10"},"type":"TEST_SUITE","name":"Deliverable-4 Corner","id":"Test Suites/Deliverable-4 Corner","source":"","message":"Test Cases/Fibonacci Page/Fibonacci - Corner","description":"","startTime":1522025797710,"endTime":1522025816609,"childRecords":[{"isOptional":false,"type":"TEST_CASE","name":"Test Cases/Factorial Page/Factorial - Corner","id":"Test Cases/Factorial Page/Factorial - Corner","source":"C:\\\\Katalon Studio\\\\Deliverable-4\\\\Test Cases\\\\Factorial Page\\\\Factorial - Corner.tc","message":"Test Cases/Factorial Page/Factorial - Corner","description":"Stress Test Factorial page","startTime":1522025798033,"endTime":1522025808235,"childRecords":[{"testStatus":{"stackTrace":"","statusValue":"INFO"},"type":"MESSAGE","name":"","message":"Evaluating variables for test case","startTime":1522025798058,"endTime":0,"childRecords":[],"interuppted":false},{"testStatus":{"stackTrace":"","statusValue":"INFO"},"type":"MESSAGE","name":"","message":"Variable \u0027Factorial_link\u0027 is set to https://cs1632ex.herokuapp.com/fact as default","startTime":1522025798097,"endTime":0,"childRecords":[],"interuppted":false},{"index":1,"isIgnoredIfFailed":false,"type":"TEST_STEP","name":"Statement - data \u003d com.kms.katalon.core.testdata.TestDataFactory.findTestData(FactorialEdgeData)","message":"Reading excel file with source file \u0027C:\\Katalon Studio\\Deliverable-4\\Data Files\\facInput edge.xlsx\u0027 and sheet name \u0027input\u0027","description":"","startTime":1522025798376,"endTime":1522025799105,"childRecords":[],"interuppted":false},{"index":2,"isIgnoredIfFailed":false,"type":"TEST_STEP","name":"openBrowser","message":"Browser is opened with url: \u0027\u0027","description":"","startTime":1522025799106,"endTime":1522025801972,"childRecords":[{"testStatus":{"stackTrace":"","statusValue":"PASSED"},"type":"MESSAGE","name":"","message":"Browser is opened with url: \u0027\u0027","startTime":1522025801972,"endTime":0,"childRecords":[],"interuppted":false}],"interuppted":false},{"index":3,"isIgnoredIfFailed":false,"type":"TEST_STEP","name":"navigateToUrl","message":"Navigate to \u0027https://cs1632ex.herokuapp.com/fact\u0027 successfully","description":"","startTime":1522025801973,"endTime":1522025802469,"childRecords":[{"testStatus":{"stackTrace":"","statusValue":"PASSED"},"type":"MESSAGE","name":"","message":"Navigate to \u0027https://cs1632ex.herokuapp.com/fact\u0027 successfully","startTime":1522025802465,"endTime":0,"childRecords":[],"interuppted":false}],"interuppted":false},{"index":4,"isIgnoredIfFailed":false,"type":"TEST_STEP","name":"Statement - For (def index : (-10..0))","message":"Navigate back successfully","description":"Loop","startTime":1522025802470,"endTime":1522025807583,"childRecords":[{"index":1,"isIgnoredIfFailed":false,"type":"TEST_STEP","name":"Statement - testString \u003d \"\" + index","description":"Force convert looping variable to string ","startTime":1522025802494,"endTime":1522025802496,"childRecords":[],"interuppted":false},{"index":2,"isIgnoredIfFailed":false,"type":"TEST_STEP","name":"Statement - outputString \u003d \"Factorial of \" + index + \" is 1!\"","description":"","startTime":1522025802497,"endTime":1522025802498,"childRecords":[],"interuppted":false},{"index":3,"isIgnoredIfFailed":false,"type":"TEST_STEP","name":"setText","message":"Text \u0027-10\u0027 is set on object \u0027Object Repository/GUI elements/Text element\u0027","description":"Use looping index as input","startTime":1522025802499,"endTime":1522025802679,"childRecords":[{"testStatus":{"stackTrace":"","statusValue":"PASSED"},"type":"MESSAGE","name":"","message":"Text \u0027-10\u0027 is set on object \u0027Object Repository/GUI elements/Text element\u0027","startTime":1522025802679,"endTime":0,"childRecords":[],"interuppted":false}],"interuppted":false},{"index":4,"isIgnoredIfFailed":false,"type":"TEST_STEP","name":"click","message":"Object: \u0027Object Repository/GUI elements/Submit button\u0027 is clicked on","description":"Click on Submit","startTime":1522025802681,"endTime":1522025802855,"childRecords":[{"testStatus":{"stackTrace":"","statusValue":"PASSED"},"type":"MESSAGE","name":"","message":"Object: \u0027Object Repository/GUI elements/Submit button\u0027 is clicked on","startTime":1522025802855,"endTime":0,"childRecords":[],"interuppted":false}],"interuppted":false},{"index":5,"isIgnoredIfFailed":false,"type":"TEST_STEP","name":"verifyElementText","message":"Actual text and expected text of test object \u0027Object Repository/GUI elements/Div jumbotron\u0027 are matched.","description":"Compare output with expected value","startTime":1522025802856,"endTime":1522025802915,"childRecords":[{"testStatus":{"stackTrace":"","statusValue":"PASSED"},"type":"MESSAGE","name":"","message":"Actual text and expected text of test object \u0027Object Repository/GUI elements/Div jumbotron\u0027 are matched.","startTime":1522025802914,"endTime":0,"childRecords":[],"interuppted":false}],"interuppted":false},{"index":6,"isIgnoredIfFailed":false,"type":"TEST_STEP","name":"back","message":"Navigate back successfully","description":"","startTime":1522025802915,"endTime":1522025802964,"childRecords":[{"testStatus":{"stackTrace":"","statusValue":"PASSED"},"type":"MESSAGE","name":"","message":"Navigate back successfully","startTime":1522025802964,"endTime":0,"childRecords":[],"interuppted":false}],"interuppted":false},{"index":1,"isIgnoredIfFailed":false,"type":"TEST_STEP","name":"Statement - testString \u003d \"\" + index","description":"Force convert looping variable to string ","startTime":1522025802965,"endTime":1522025802965,"childRecords":[],"interuppted":false},{"index":2,"isIgnoredIfFailed":false,"type":"TEST_STEP","name":"Statement - outputString \u003d \"Factorial of \" + index + \" is 1!\"","description":"","startTime":1522025802965,"endTime":1522025802966,"childRecords":[],"interuppted":false},{"index":3,"isIgnoredIfFailed":false,"type":"TEST_STEP","name":"setText","message":"Text \u0027-9\u0027 is set on object \u0027Object Repository/GUI elements/Text element\u0027","description":"Use looping index as input","startTime":1522025802966,"endTime":1522025803062,"childRecords":[{"testStatus":{"stackTrace":"","statusValue":"PASSED"},"type":"MESSAGE","name":"","message":"Text \u0027-9\u0027 is set on object \u0027Object Repository/GUI elements/Text element\u0027","startTime":1522025803062,"endTime":0,"childRecords":[],"interuppted":false}],"interuppted":false},{"index":4,"isIgnoredIfFailed":false,"type":"TEST_STEP","name":"click","message":"Object: \u0027Object Repository/GUI elements/Submit button\u0027 is clicked on","description":"Click on Submit","startTime":1522025803062,"endTime":1522025803265,"childRecords":[{"testStatus":{"stackTrace":"","statusValue":"PASSED"},"type":"MESSAGE","name":"","message":"Object: \u0027Object Repository/GUI elements/Submit button\u0027 is clicked on","startTime":1522025803264,"endTime":0,"childRecords":[],"interuppted":false}],"interuppted":false},{"index":5,"isIgnoredIfFailed":false,"type":"TEST_STEP","name":"verifyElementText","message":"Actual text and expected text of test object \u0027Object Repository/GUI elements/Div jumbotron\u0027 are matched.","description":"Compare output with expected value","startTime":1522025803265,"endTime":1522025803335,"childRecords":[{"testStatus":{"stackTrace":"","statusValue":"PASSED"},"type":"MESSAGE","name":"","message":"Actual text and expected text of test object \u0027Object Repository/GUI elements/Div jumbotron\u0027 are matched.","startTime":1522025803335,"endTime":0,"childRecords":[],"interuppted":false}],"interuppted":false},{"index":6,"isIgnoredIfFailed":false,"type":"TEST_STEP","name":"back","message":"Navigate back successfully","description":"","startTime":1522025803336,"endTime":1522025803403,"childRecords":[{"testStatus":{"stackTrace":"","statusValue":"PASSED"},"type":"MESSAGE","name":"","message":"Navigate back successfully","startTime":1522025803401,"endTime":0,"childRecords":[],"interuppted":false}],"interuppted":false},{"index":1,"isIgnoredIfFailed":false,"type":"TEST_STEP","name":"Statement - testString \u003d \"\" + index","description":"Force convert looping variable to string ","startTime":1522025803403,"endTime":1522025803404,"childRecords":[],"interuppted":false},{"index":2,"isIgnoredIfFailed":false,"type":"TEST_STEP","name":"Statement - outputString \u003d \"Factorial of \" + index + \" is 1!\"","description":"","startTime":1522025803404,"endTime":1522025803405,"childRecords":[],"interuppted":false},{"index":3,"isIgnoredIfFailed":false,"type":"TEST_STEP","name":"setText","message":"Text \u0027-8\u0027 is set on object \u0027Object Repository/GUI elements/Text element\u0027","description":"Use looping index as input","startTime":1522025803405,"endTime":1522025803524,"childRecords":[{"testStatus":{"stackTrace":"","statusValue":"PASSED"},"type":"MESSAGE","name":"","message":"Text \u0027-8\u0027 is set on object \u0027Object Repository/GUI elements/Text element\u0027","startTime":1522025803523,"endTime":0,"childRecords":[],"interuppted":false}],"interuppted":false},{"index":4,"isIgnoredIfFailed":false,"type":"TEST_STEP","name":"click","message":"Object: \u0027Object Repository/GUI elements/Submit button\u0027 is clicked on","description":"Click on Submit","startTime":1522025803524,"endTime":1522025803745,"childRecords":[{"testStatus":{"stackTrace":"","statusValue":"PASSED"},"type":"MESSAGE","name":"","message":"Object: \u0027Object Repository/GUI elements/Submit button\u0027 is clicked on","startTime":1522025803744,"endTime":0,"childRecords":[],"interuppted":false}],"interuppted":false},{"index":5,"isIgnoredIfFailed":false,"type":"TEST_STEP","name":"verifyElementText","message":"Actual text and expected text of test object \u0027Object Repository/GUI elements/Div jumbotron\u0027 are matched.","description":"Compare output with expected value","startTime":1522025803745,"endTime":1522025803806,"childRecords":[{"testStatus":{"stackTrace":"","statusValue":"PASSED"},"type":"MESSAGE","name":"","message":"Actual text and expected text of test object \u0027Object Repository/GUI elements/Div jumbotron\u0027 are matched.","startTime":1522025803806,"endTime":0,"childRecords":[],"interuppted":false}],"interuppted":false},{"index":6,"isIgnoredIfFailed":false,"type":"TEST_STEP","name":"back","message":"Navigate back successfully","description":"","startTime":1522025803807,"endTime":1522025803868,"childRecords":[{"testStatus":{"stackTrace":"","statusValue":"PASSED"},"type":"MESSAGE","name":"","message":"Navigate back successfully","startTime":1522025803867,"endTime":0,"childRecords":[],"interuppted":false}],"interuppted":false},{"index":1,"isIgnoredIfFailed":false,"type":"TEST_STEP","name":"Statement - testString \u003d \"\" + index","description":"Force convert looping variable to string ","startTime":1522025803869,"endTime":1522025803870,"childRecords":[],"interuppted":false},{"index":2,"isIgnoredIfFailed":false,"type":"TEST_STEP","name":"Statement - outputString \u003d \"Factorial of \" + index + \" is 1!\"","description":"","startTime":1522025803871,"endTime":1522025803872,"childRecords":[],"interuppted":false},{"index":3,"isIgnoredIfFailed":false,"type":"TEST_STEP","name":"setText","message":"Text \u0027-7\u0027 is set on object \u0027Object Repository/GUI elements/Text element\u0027","description":"Use looping index as input","startTime":1522025803873,"endTime":1522025804001,"childRecords":[{"testStatus":{"stackTrace":"","statusValue":"PASSED"},"type":"MESSAGE","name":"","message":"Text \u0027-7\u0027 is set on object \u0027Object Repository/GUI elements/Text element\u0027","startTime":1522025804000,"endTime":0,"childRecords":[],"interuppted":false}],"interuppted":false},{"index":4,"isIgnoredIfFailed":false,"type":"TEST_STEP","name":"click","message":"Object: \u0027Object Repository/GUI elements/Submit button\u0027 is clicked on","description":"Click on Submit","startTime":1522025804001,"endTime":1522025804259,"childRecords":[{"testStatus":{"stackTrace":"","statusValue":"PASSED"},"type":"MESSAGE","name":"","message":"Object: \u0027Object Repository/GUI elements/Submit button\u0027 is clicked on","startTime":1522025804257,"endTime":0,"childRecords":[],"interuppted":false}],"interuppted":false},{"index":5,"isIgnoredIfFailed":false,"type":"TEST_STEP","name":"verifyElementText","message":"Actual text and expected text of test object \u0027Object Repository/GUI elements/Div jumbotron\u0027 are matched.","description":"Compare output with expected value","startTime":1522025804259,"endTime":1522025804359,"childRecords":[{"testStatus":{"stackTrace":"","statusValue":"PASSED"},"type":"MESSAGE","name":"","message":"Actual text and expected text of test object \u0027Object Repository/GUI elements/Div jumbotron\u0027 are matched.","startTime":1522025804359,"endTime":0,"childRecords":[],"interuppted":false}],"interuppted":false},{"index":6,"isIgnoredIfFailed":false,"type":"TEST_STEP","name":"back","message":"Navigate back successfully","description":"","startTime":1522025804360,"endTime":1522025804430,"childRecords":[{"testStatus":{"stackTrace":"","statusValue":"PASSED"},"type":"MESSAGE","name":"","message":"Navigate back successfully","startTime":1522025804429,"endTime":0,"childRecords":[],"interuppted":false}],"interuppted":false},{"index":1,"isIgnoredIfFailed":false,"type":"TEST_STEP","name":"Statement - testString \u003d \"\" + index","description":"Force convert looping variable to string ","startTime":1522025804430,"endTime":1522025804431,"childRecords":[],"interuppted":false},{"index":2,"isIgnoredIfFailed":false,"type":"TEST_STEP","name":"Statement - outputString \u003d \"Factorial of \" + index + \" is 1!\"","description":"","startTime":1522025804431,"endTime":1522025804431,"childRecords":[],"interuppted":false},{"index":3,"isIgnoredIfFailed":false,"type":"TEST_STEP","name":"setText","message":"Text \u0027-6\u0027 is set on object \u0027Object Repository/GUI elements/Text element\u0027","description":"Use looping index as input","startTime":1522025804432,"endTime":1522025804583,"childRecords":[{"testStatus":{"stackTrace":"","statusValue":"PASSED"},"type":"MESSAGE","name":"","message":"Text \u0027-6\u0027 is set on object \u0027Object Repository/GUI elements/Text element\u0027","startTime":1522025804582,"endTime":0,"childRecords":[],"interuppted":false}],"interuppted":false},{"index":4,"isIgnoredIfFailed":false,"type":"TEST_STEP","name":"click","message":"Object: \u0027Object Repository/GUI elements/Submit button\u0027 is clicked on","description":"Click on Submit","startTime":1522025804583,"endTime":1522025804834,"childRecords":[{"testStatus":{"stackTrace":"","statusValue":"PASSED"},"type":"MESSAGE","name":"","message":"Object: \u0027Object Repository/GUI elements/Submit button\u0027 is clicked on","startTime":1522025804834,"endTime":0,"childRecords":[],"interuppted":false}],"interuppted":false},{"index":5,"isIgnoredIfFailed":false,"type":"TEST_STEP","name":"verifyElementText","message":"Actual text and expected text of test object \u0027Object Repository/GUI elements/Div jumbotron\u0027 are matched.","description":"Compare output with expected value","startTime":1522025804835,"endTime":1522025804937,"childRecords":[{"testStatus":{"stackTrace":"","statusValue":"PASSED"},"type":"MESSAGE","name":"","message":"Actual text and expected text of test object \u0027Object Repository/GUI elements/Div jumbotron\u0027 are matched.","startTime":1522025804936,"endTime":0,"childRecords":[],"interuppted":false}],"interuppted":false},{"index":6,"isIgnoredIfFailed":false,"type":"TEST_STEP","name":"back","message":"Navigate back successfully","description":"","startTime":1522025804937,"endTime":1522025805032,"childRecords":[{"testStatus":{"stackTrace":"","statusValue":"PASSED"},"type":"MESSAGE","name":"","message":"Navigate back successfully","startTime":1522025805030,"endTime":0,"childRecords":[],"interuppted":false}],"interuppted":false},{"index":1,"isIgnoredIfFailed":false,"type":"TEST_STEP","name":"Statement - testString \u003d \"\" + index","description":"Force convert looping variable to string ","startTime":1522025805032,"endTime":1522025805033,"childRecords":[],"interuppted":false},{"index":2,"isIgnoredIfFailed":false,"type":"TEST_STEP","name":"Statement - outputString \u003d \"Factorial of \" + index + \" is 1!\"","description":"","startTime":1522025805034,"endTime":1522025805035,"childRecords":[],"interuppted":false},{"index":3,"isIgnoredIfFailed":false,"type":"TEST_STEP","name":"setText","message":"Text \u0027-5\u0027 is set on object \u0027Object Repository/GUI elements/Text element\u0027","description":"Use looping index as input","startTime":1522025805036,"endTime":1522025805201,"childRecords":[{"testStatus":{"stackTrace":"","statusValue":"PASSED"},"type":"MESSAGE","name":"","message":"Text \u0027-5\u0027 is set on object \u0027Object Repository/GUI elements/Text element\u0027","startTime":1522025805200,"endTime":0,"childRecords":[],"interuppted":false}],"interuppted":false},{"index":4,"isIgnoredIfFailed":false,"type":"TEST_STEP","name":"click","message":"Object: \u0027Object Repository/GUI elements/Submit button\u0027 is clicked on","description":"Click on Submit","startTime":1522025805202,"endTime":1522025805394,"childRecords":[{"testStatus":{"stackTrace":"","statusValue":"PASSED"},"type":"MESSAGE","name":"","message":"Object: \u0027Object Repository/GUI elements/Submit button\u0027 is clicked on","startTime":1522025805393,"endTime":0,"childRecords":[],"interuppted":false}],"interuppted":false},{"index":5,"isIgnoredIfFailed":false,"type":"TEST_STEP","name":"verifyElementText","message":"Actual text and expected text of test object \u0027Object Repository/GUI elements/Div jumbotron\u0027 are matched.","description":"Compare output with expected value","startTime":1522025805394,"endTime":1522025805450,"childRecords":[{"testStatus":{"stackTrace":"","statusValue":"PASSED"},"type":"MESSAGE","name":"","message":"Actual text and expected text of test object \u0027Object Repository/GUI elements/Div jumbotron\u0027 are matched.","startTime":1522025805449,"endTime":0,"childRecords":[],"interuppted":false}],"interuppted":false},{"index":6,"isIgnoredIfFailed":false,"type":"TEST_STEP","name":"back","message":"Navigate back successfully","description":"","startTime":1522025805450,"endTime":1522025805515,"childRecords":[{"testStatus":{"stackTrace":"","statusValue":"PASSED"},"type":"MESSAGE","name":"","message":"Navigate back successfully","startTime":1522025805514,"endTime":0,"childRecords":[],"interuppted":false}],"interuppted":false},{"index":1,"isIgnoredIfFailed":false,"type":"TEST_STEP","name":"Statement - testString \u003d \"\" + index","description":"Force convert looping variable to string ","startTime":1522025805515,"endTime":1522025805516,"childRecords":[],"interuppted":false},{"index":2,"isIgnoredIfFailed":false,"type":"TEST_STEP","name":"Statement - outputString \u003d \"Factorial of \" + index + \" is 1!\"","description":"","startTime":1522025805516,"endTime":1522025805517,"childRecords":[],"interuppted":false},{"index":3,"isIgnoredIfFailed":false,"type":"TEST_STEP","name":"setText","message":"Text \u0027-4\u0027 is set on object \u0027Object Repository/GUI elements/Text element\u0027","description":"Use looping index as input","startTime":1522025805517,"endTime":1522025805650,"childRecords":[{"testStatus":{"stackTrace":"","statusValue":"PASSED"},"type":"MESSAGE","name":"","message":"Text \u0027-4\u0027 is set on object \u0027Object Repository/GUI elements/Text element\u0027","startTime":1522025805649,"endTime":0,"childRecords":[],"interuppted":false}],"interuppted":false},{"index":4,"isIgnoredIfFailed":false,"type":"TEST_STEP","name":"click","message":"Object: \u0027Object Repository/GUI elements/Submit button\u0027 is clicked on","description":"Click on Submit","startTime":1522025805650,"endTime":1522025805796,"childRecords":[{"testStatus":{"stackTrace":"","statusValue":"PASSED"},"type":"MESSAGE","name":"","message":"Object: \u0027Object Repository/GUI elements/Submit button\u0027 is clicked on","startTime":1522025805795,"endTime":0,"childRecords":[],"interuppted":false}],"interuppted":false},{"index":5,"isIgnoredIfFailed":false,"type":"TEST_STEP","name":"verifyElementText","message":"Actual text and expected text of test object \u0027Object Repository/GUI elements/Div jumbotron\u0027 are matched.","description":"Compare output with expected value","startTime":1522025805796,"endTime":1522025805832,"childRecords":[{"testStatus":{"stackTrace":"","statusValue":"PASSED"},"type":"MESSAGE","name":"","message":"Actual text and expected text of test object \u0027Object Repository/GUI elements/Div jumbotron\u0027 are matched.","startTime":1522025805831,"endTime":0,"childRecords":[],"interuppted":false}],"interuppted":false},{"index":6,"isIgnoredIfFailed":false,"type":"TEST_STEP","name":"back","message":"Navigate back successfully","description":"","startTime":1522025805832,"endTime":1522025805865,"childRecords":[{"testStatus":{"stackTrace":"","statusValue":"PASSED"},"type":"MESSAGE","name":"","message":"Navigate back successfully","startTime":1522025805864,"endTime":0,"childRecords":[],"interuppted":false}],"interuppted":false},{"index":1,"isIgnoredIfFailed":false,"type":"TEST_STEP","name":"Statement - testString \u003d \"\" + index","description":"Force convert looping variable to string ","startTime":1522025805865,"endTime":1522025805865,"childRecords":[],"interuppted":false},{"index":2,"isIgnoredIfFailed":false,"type":"TEST_STEP","name":"Statement - outputString \u003d \"Factorial of \" + index + \" is 1!\"","description":"","startTime":1522025805865,"endTime":1522025805865,"childRecords":[],"interuppted":false},{"index":3,"isIgnoredIfFailed":false,"type":"TEST_STEP","name":"setText","message":"Text \u0027-3\u0027 is set on object \u0027Object Repository/GUI elements/Text element\u0027","description":"Use looping index as input","startTime":1522025805866,"endTime":1522025805957,"childRecords":[{"testStatus":{"stackTrace":"","statusValue":"PASSED"},"type":"MESSAGE","name":"","message":"Text \u0027-3\u0027 is set on object \u0027Object Repository/GUI elements/Text element\u0027","startTime":1522025805956,"endTime":0,"childRecords":[],"interuppted":false}],"interuppted":false},{"index":4,"isIgnoredIfFailed":false,"type":"TEST_STEP","name":"click","message":"Object: \u0027Object Repository/GUI elements/Submit button\u0027 is clicked on","description":"Click on Submit","startTime":1522025805957,"endTime":1522025806105,"childRecords":[{"testStatus":{"stackTrace":"","statusValue":"PASSED"},"type":"MESSAGE","name":"","message":"Object: \u0027Object Repository/GUI elements/Submit button\u0027 is clicked on","startTime":1522025806104,"endTime":0,"childRecords":[],"interuppted":false}],"interuppted":false},{"index":5,"isIgnoredIfFailed":false,"type":"TEST_STEP","name":"verifyElementText","message":"Actual text and expected text of test object \u0027Object Repository/GUI elements/Div jumbotron\u0027 are matched.","description":"Compare output with expected value","startTime":1522025806105,"endTime":1522025806187,"childRecords":[{"testStatus":{"stackTrace":"","statusValue":"PASSED"},"type":"MESSAGE","name":"","message":"Actual text and expected text of test object \u0027Object Repository/GUI elements/Div jumbotron\u0027 are matched.","startTime":1522025806187,"endTime":0,"childRecords":[],"interuppted":false}],"interuppted":false},{"index":6,"isIgnoredIfFailed":false,"type":"TEST_STEP","name":"back","message":"Navigate back successfully","description":"","startTime":1522025806188,"endTime":1522025806241,"childRecords":[{"testStatus":{"stackTrace":"","statusValue":"PASSED"},"type":"MESSAGE","name":"","message":"Navigate back successfully","startTime":1522025806241,"endTime":0,"childRecords":[],"interuppted":false}],"interuppted":false},{"index":1,"isIgnoredIfFailed":false,"type":"TEST_STEP","name":"Statement - testString \u003d \"\" + index","description":"Force convert looping variable to string ","startTime":1522025806242,"endTime":1522025806242,"childRecords":[],"interuppted":false},{"index":2,"isIgnoredIfFailed":false,"type":"TEST_STEP","name":"Statement - outputString \u003d \"Factorial of \" + index + \" is 1!\"","description":"","startTime":1522025806243,"endTime":1522025806243,"childRecords":[],"interuppted":false},{"index":3,"isIgnoredIfFailed":false,"type":"TEST_STEP","name":"setText","message":"Text \u0027-2\u0027 is set on object \u0027Object Repository/GUI elements/Text element\u0027","description":"Use looping index as input","startTime":1522025806243,"endTime":1522025806374,"childRecords":[{"testStatus":{"stackTrace":"","statusValue":"PASSED"},"type":"MESSAGE","name":"","message":"Text \u0027-2\u0027 is set on object \u0027Object Repository/GUI elements/Text element\u0027","startTime":1522025806373,"endTime":0,"childRecords":[],"interuppted":false}],"interuppted":false},{"index":4,"isIgnoredIfFailed":false,"type":"TEST_STEP","name":"click","message":"Object: \u0027Object Repository/GUI elements/Submit button\u0027 is clicked on","description":"Click on Submit","startTime":1522025806374,"endTime":1522025806537,"childRecords":[{"testStatus":{"stackTrace":"","statusValue":"PASSED"},"type":"MESSAGE","name":"","message":"Object: \u0027Object Repository/GUI elements/Submit button\u0027 is clicked on","startTime":1522025806537,"endTime":0,"childRecords":[],"interuppted":false}],"interuppted":false},{"index":5,"isIgnoredIfFailed":false,"type":"TEST_STEP","name":"verifyElementText","message":"Actual text and expected text of test object \u0027Object Repository/GUI elements/Div jumbotron\u0027 are matched.","description":"Compare output with expected value","startTime":1522025806537,"endTime":1522025806595,"childRecords":[{"testStatus":{"stackTrace":"","statusValue":"PASSED"},"type":"MESSAGE","name":"","message":"Actual text and expected text of test object \u0027Object Repository/GUI elements/Div jumbotron\u0027 are matched.","startTime":1522025806594,"endTime":0,"childRecords":[],"interuppted":false}],"interuppted":false},{"index":6,"isIgnoredIfFailed":false,"type":"TEST_STEP","name":"back","message":"Navigate back successfully","description":"","startTime":1522025806595,"endTime":1522025806676,"childRecords":[{"testStatus":{"stackTrace":"","statusValue":"PASSED"},"type":"MESSAGE","name":"","message":"Navigate back successfully","startTime":1522025806675,"endTime":0,"childRecords":[],"interuppted":false}],"interuppted":false},{"index":1,"isIgnoredIfFailed":false,"type":"TEST_STEP","name":"Statement - testString \u003d \"\" + index","description":"Force convert looping variable to string ","startTime":1522025806677,"endTime":1522025806677,"childRecords":[],"interuppted":false},{"index":2,"isIgnoredIfFailed":false,"type":"TEST_STEP","name":"Statement - outputString \u003d \"Factorial of \" + index + \" is 1!\"","description":"","startTime":1522025806677,"endTime":1522025806677,"childRecords":[],"interuppted":false},{"index":3,"isIgnoredIfFailed":false,"type":"TEST_STEP","name":"setText","message":"Text \u0027-1\u0027 is set on object \u0027Object Repository/GUI elements/Text element\u0027","description":"Use looping index as input","startTime":1522025806677,"endTime":1522025806825,"childRecords":[{"testStatus":{"stackTrace":"","statusValue":"PASSED"},"type":"MESSAGE","name":"","message":"Text \u0027-1\u0027 is set on object \u0027Object Repository/GUI elements/Text element\u0027","startTime":1522025806825,"endTime":0,"childRecords":[],"interuppted":false}],"interuppted":false},{"index":4,"isIgnoredIfFailed":false,"type":"TEST_STEP","name":"click","message":"Object: \u0027Object Repository/GUI elements/Submit button\u0027 is clicked on","description":"Click on Submit","startTime":1522025806825,"endTime":1522025806985,"childRecords":[{"testStatus":{"stackTrace":"","statusValue":"PASSED"},"type":"MESSAGE","name":"","message":"Object: \u0027Object Repository/GUI elements/Submit button\u0027 is clicked on","startTime":1522025806984,"endTime":0,"childRecords":[],"interuppted":false}],"interuppted":false},{"index":5,"isIgnoredIfFailed":false,"type":"TEST_STEP","name":"verifyElementText","message":"Actual text and expected text of test object \u0027Object Repository/GUI elements/Div jumbotron\u0027 are matched.","description":"Compare output with expected value","startTime":1522025806986,"endTime":1522025807035,"childRecords":[{"testStatus":{"stackTrace":"","statusValue":"PASSED"},"type":"MESSAGE","name":"","message":"Actual text and expected text of test object \u0027Object Repository/GUI elements/Div jumbotron\u0027 are matched.","startTime":1522025807035,"endTime":0,"childRecords":[],"interuppted":false}],"interuppted":false},{"index":6,"isIgnoredIfFailed":false,"type":"TEST_STEP","name":"back","message":"Navigate back successfully","description":"","startTime":1522025807036,"endTime":1522025807089,"childRecords":[{"testStatus":{"stackTrace":"","statusValue":"PASSED"},"type":"MESSAGE","name":"","message":"Navigate back successfully","startTime":1522025807089,"endTime":0,"childRecords":[],"interuppted":false}],"interuppted":false},{"index":1,"isIgnoredIfFailed":false,"type":"TEST_STEP","name":"Statement - testString \u003d \"\" + index","description":"Force convert looping variable to string ","startTime":1522025807089,"endTime":1522025807090,"childRecords":[],"interuppted":false},{"index":2,"isIgnoredIfFailed":false,"type":"TEST_STEP","name":"Statement - outputString \u003d \"Factorial of \" + index + \" is 1!\"","description":"","startTime":1522025807090,"endTime":1522025807090,"childRecords":[],"interuppted":false},{"index":3,"isIgnoredIfFailed":false,"type":"TEST_STEP","name":"setText","message":"Text \u00270\u0027 is set on object \u0027Object Repository/GUI elements/Text element\u0027","description":"Use looping index as input","startTime":1522025807090,"endTime":1522025807220,"childRecords":[{"testStatus":{"stackTrace":"","statusValue":"PASSED"},"type":"MESSAGE","name":"","message":"Text \u00270\u0027 is set on object \u0027Object Repository/GUI elements/Text element\u0027","startTime":1522025807220,"endTime":0,"childRecords":[],"interuppted":false}],"interuppted":false},{"index":4,"isIgnoredIfFailed":false,"type":"TEST_STEP","name":"click","message":"Object: \u0027Object Repository/GUI elements/Submit button\u0027 is clicked on","description":"Click on Submit","startTime":1522025807221,"endTime":1522025807454,"childRecords":[{"testStatus":{"stackTrace":"","statusValue":"PASSED"},"type":"MESSAGE","name":"","message":"Object: \u0027Object Repository/GUI elements/Submit button\u0027 is clicked on","startTime":1522025807454,"endTime":0,"childRecords":[],"interuppted":false}],"interuppted":false},{"index":5,"isIgnoredIfFailed":false,"type":"TEST_STEP","name":"verifyElementText","message":"Actual text and expected text of test object \u0027Object Repository/GUI elements/Div jumbotron\u0027 are matched.","description":"Compare output with expected value","startTime":1522025807455,"endTime":1522025807512,"childRecords":[{"testStatus":{"stackTrace":"","statusValue":"PASSED"},"type":"MESSAGE","name":"","message":"Actual text and expected text of test object \u0027Object Repository/GUI elements/Div jumbotron\u0027 are matched.","startTime":1522025807512,"endTime":0,"childRecords":[],"interuppted":false}],"interuppted":false},{"index":6,"isIgnoredIfFailed":false,"type":"TEST_STEP","name":"back","message":"Navigate back successfully","description":"","startTime":1522025807512,"endTime":1522025807583,"childRecords":[{"testStatus":{"stackTrace":"","statusValue":"PASSED"},"type":"MESSAGE","name":"","message":"Navigate back successfully","startTime":1522025807582,"endTime":0,"childRecords":[],"interuppted":false}],"interuppted":false}],"interuppted":false},{"index":5,"isIgnoredIfFailed":false,"type":"TEST_STEP","name":"closeBrowser","message":"Browser is closed","description":"","startTime":1522025807583,"endTime":1522025808234,"childRecords":[{"testStatus":{"stackTrace":"","statusValue":"PASSED"},"type":"MESSAGE","name":"","message":"Browser is closed","startTime":1522025808233,"endTime":0,"childRecords":[],"interuppted":false}],"interuppted":false},{"testStatus":{"stackTrace":"","statusValue":"PASSED"},"type":"MESSAGE","name":"","message":"Test Cases/Factorial Page/Factorial - Corner","startTime":1522025808234,"endTime":0,"childRecords":[],"interuppted":false}],"interuppted":false},{"isOptional":false,"type":"TEST_CASE","name":"Test Cases/Fibonacci Page/Fibonacci - Corner","id":"Test Cases/Fibonacci Page/Fibonacci - Corner","source":"C:\\\\Katalon Studio\\\\Deliverable-4\\\\Test Cases\\\\Fibonacci Page\\\\Fibonacci - Corner.tc","message":"Test Cases/Fibonacci Page/Fibonacci - Corner","description":"Stress Test Factorial page","startTime":1522025808241,"endTime":1522025816555,"childRecords":[{"testStatus":{"stackTrace":"","statusValue":"INFO"},"type":"MESSAGE","name":"","message":"Evaluating variables for test case","startTime":1522025808255,"endTime":0,"childRecords":[],"interuppted":false},{"testStatus":{"stackTrace":"","statusValue":"INFO"},"type":"MESSAGE","name":"","message":"Variable \u0027Fibonacci_link\u0027 is set to https://cs1632ex.herokuapp.com/fib as default","startTime":1522025808285,"endTime":0,"childRecords":[],"interuppted":false},{"index":1,"isIgnoredIfFailed":false,"type":"TEST_STEP","name":"Statement - data \u003d com.kms.katalon.core.testdata.TestDataFactory.findTestData(FactorialEdgeData)","message":"Reading excel file with source file \u0027C:\\Katalon Studio\\Deliverable-4\\Data Files\\facInput edge.xlsx\u0027 and sheet name \u0027input\u0027","description":"","startTime":1522025808432,"endTime":1522025808465,"childRecords":[],"interuppted":false},{"index":2,"isIgnoredIfFailed":false,"type":"TEST_STEP","name":"openBrowser","message":"Browser is opened with url: \u0027\u0027","description":"","startTime":1522025808466,"endTime":1522025810529,"childRecords":[{"testStatus":{"stackTrace":"","statusValue":"PASSED"},"type":"MESSAGE","name":"","message":"Browser is opened with url: \u0027\u0027","startTime":1522025810528,"endTime":0,"childRecords":[],"interuppted":false}],"interuppted":false},{"index":3,"isIgnoredIfFailed":false,"type":"TEST_STEP","name":"navigateToUrl","message":"Navigate to \u0027https://cs1632ex.herokuapp.com/fib\u0027 successfully","description":"","startTime":1522025810529,"endTime":1522025811077,"childRecords":[{"testStatus":{"stackTrace":"","statusValue":"PASSED"},"type":"MESSAGE","name":"","message":"Navigate to \u0027https://cs1632ex.herokuapp.com/fib\u0027 successfully","startTime":1522025811076,"endTime":0,"childRecords":[],"interuppted":false}],"interuppted":false},{"index":4,"isIgnoredIfFailed":false,"type":"TEST_STEP","name":"Statement - For (def index : (1000..1010))","message":"Navigate back successfully","description":"Loop","startTime":1522025811077,"endTime":1522025815935,"childRecords":[{"index":1,"isIgnoredIfFailed":false,"type":"TEST_STEP","name":"Statement - testString \u003d \"\" + index","description":"","startTime":1522025811079,"endTime":1522025811079,"childRecords":[],"interuppted":false},{"index":2,"isIgnoredIfFailed":false,"type":"TEST_STEP","name":"Statement - outputString \u003d \"Fibonacci of \" + index + \" is 1!\"","description":"","startTime":1522025811080,"endTime":1522025811081,"childRecords":[],"interuppted":false},{"index":3,"isIgnoredIfFailed":false,"type":"TEST_STEP","name":"setText","message":"Text \u00271000\u0027 is set on object \u0027Object Repository/GUI elements/Text element\u0027","description":"Use looping index as input","startTime":1522025811081,"endTime":1522025811220,"childRecords":[{"testStatus":{"stackTrace":"","statusValue":"PASSED"},"type":"MESSAGE","name":"","message":"Text \u00271000\u0027 is set on object \u0027Object Repository/GUI elements/Text element\u0027","startTime":1522025811219,"endTime":0,"childRecords":[],"interuppted":false}],"interuppted":false},{"index":4,"isIgnoredIfFailed":false,"type":"TEST_STEP","name":"click","message":"Object: \u0027Object Repository/GUI elements/Submit button\u0027 is clicked on","description":"Click on Submit","startTime":1522025811220,"endTime":1522025811518,"childRecords":[{"testStatus":{"stackTrace":"","statusValue":"PASSED"},"type":"MESSAGE","name":"","message":"Object: \u0027Object Repository/GUI elements/Submit button\u0027 is clicked on","startTime":1522025811517,"endTime":0,"childRecords":[],"interuppted":false}],"interuppted":false},{"index":5,"isIgnoredIfFailed":false,"type":"TEST_STEP","name":"verifyElementText","message":"Actual text and expected text of test object \u0027Object Repository/GUI elements/Div jumbotron\u0027 are matched.","description":"Compare output with expected value","startTime":1522025811518,"endTime":1522025811635,"childRecords":[{"testStatus":{"stackTrace":"","statusValue":"PASSED"},"type":"MESSAGE","name":"","message":"Actual text and expected text of test object \u0027Object Repository/GUI elements/Div jumbotron\u0027 are matched.","startTime":1522025811634,"endTime":0,"childRecords":[],"interuppted":false}],"interuppted":false},{"index":6,"isIgnoredIfFailed":false,"type":"TEST_STEP","name":"back","message":"Navigate back successfully","description":"","startTime":1522025811635,"endTime":1522025811718,"childRecords":[{"testStatus":{"stackTrace":"","statusValue":"PASSED"},"type":"MESSAGE","name":"","message":"Navigate back successfully","startTime":1522025811718,"endTime":0,"childRecords":[],"interuppted":false}],"interuppted":false},{"index":1,"isIgnoredIfFailed":false,"type":"TEST_STEP","name":"Statement - testString \u003d \"\" + index","description":"","startTime":1522025811718,"endTime":1522025811719,"childRecords":[],"interuppted":false},{"index":2,"isIgnoredIfFailed":false,"type":"TEST_STEP","name":"Statement - outputString \u003d \"Fibonacci of \" + index + \" is 1!\"","description":"","startTime":1522025811719,"endTime":1522025811719,"childRecords":[],"interuppted":false},{"index":3,"isIgnoredIfFailed":false,"type":"TEST_STEP","name":"setText","message":"Text \u00271001\u0027 is set on object \u0027Object Repository/GUI elements/Text element\u0027","description":"Use looping index as input","startTime":1522025811719,"endTime":1522025811814,"childRecords":[{"testStatus":{"stackTrace":"","statusValue":"PASSED"},"type":"MESSAGE","name":"","message":"Text \u00271001\u0027 is set on object \u0027Object Repository/GUI elements/Text element\u0027","startTime":1522025811813,"endTime":0,"childRecords":[],"interuppted":false}],"interuppted":false},{"index":4,"isIgnoredIfFailed":false,"type":"TEST_STEP","name":"click","message":"Object: \u0027Object Repository/GUI elements/Submit button\u0027 is clicked on","description":"Click on Submit","startTime":1522025811814,"endTime":1522025812034,"childRecords":[{"testStatus":{"stackTrace":"","statusValue":"PASSED"},"type":"MESSAGE","name":"","message":"Object: \u0027Object Repository/GUI elements/Submit button\u0027 is clicked on","startTime":1522025812034,"endTime":0,"childRecords":[],"interuppted":false}],"interuppted":false},{"index":5,"isIgnoredIfFailed":false,"type":"TEST_STEP","name":"verifyElementText","message":"Actual text and expected text of test object \u0027Object Repository/GUI elements/Div jumbotron\u0027 are matched.","description":"Compare output with expected value","startTime":1522025812034,"endTime":1522025812108,"childRecords":[{"testStatus":{"stackTrace":"","statusValue":"PASSED"},"type":"MESSAGE","name":"","message":"Actual text and expected text of test object \u0027Object Repository/GUI elements/Div jumbotron\u0027 are matched.","startTime":1522025812108,"endTime":0,"childRecords":[],"interuppted":false}],"interuppted":false},{"index":6,"isIgnoredIfFailed":false,"type":"TEST_STEP","name":"back","message":"Navigate back successfully","description":"","startTime":1522025812109,"endTime":1522025812177,"childRecords":[{"testStatus":{"stackTrace":"","statusValue":"PASSED"},"type":"MESSAGE","name":"","message":"Navigate back successfully","startTime":1522025812176,"endTime":0,"childRecords":[],"interuppted":false}],"interuppted":false},{"index":1,"isIgnoredIfFailed":false,"type":"TEST_STEP","name":"Statement - testString \u003d \"\" + index","description":"","startTime":1522025812177,"endTime":1522025812177,"childRecords":[],"interuppted":false},{"index":2,"isIgnoredIfFailed":false,"type":"TEST_STEP","name":"Statement - outputString \u003d \"Fibonacci of \" + index + \" is 1!\"","description":"","startTime":1522025812177,"endTime":1522025812178,"childRecords":[],"interuppted":false},{"index":3,"isIgnoredIfFailed":false,"type":"TEST_STEP","name":"setText","message":"Text \u00271002\u0027 is set on object \u0027Object Repository/GUI elements/Text element\u0027","description":"Use looping index as input","startTime":1522025812178,"endTime":1522025812291,"childRecords":[{"testStatus":{"stackTrace":"","statusValue":"PASSED"},"type":"MESSAGE","name":"","message":"Text \u00271002\u0027 is set on object \u0027Object Repository/GUI elements/Text element\u0027","startTime":1522025812291,"endTime":0,"childRecords":[],"interuppted":false}],"interuppted":false},{"index":4,"isIgnoredIfFailed":false,"type":"TEST_STEP","name":"click","message":"Object: \u0027Object Repository/GUI elements/Submit button\u0027 is clicked on","description":"Click on Submit","startTime":1522025812291,"endTime":1522025812435,"childRecords":[{"testStatus":{"stackTrace":"","statusValue":"PASSED"},"type":"MESSAGE","name":"","message":"Object: \u0027Object Repository/GUI elements/Submit button\u0027 is clicked on","startTime":1522025812435,"endTime":0,"childRecords":[],"interuppted":false}],"interuppted":false},{"index":5,"isIgnoredIfFailed":false,"type":"TEST_STEP","name":"verifyElementText","message":"Actual text and expected text of test object \u0027Object Repository/GUI elements/Div jumbotron\u0027 are matched.","description":"Compare output with expected value","startTime":1522025812436,"endTime":1522025812470,"childRecords":[{"testStatus":{"stackTrace":"","statusValue":"PASSED"},"type":"MESSAGE","name":"","message":"Actual text and expected text of test object \u0027Object Repository/GUI elements/Div jumbotron\u0027 are matched.","startTime":1522025812470,"endTime":0,"childRecords":[],"interuppted":false}],"interuppted":false},{"index":6,"isIgnoredIfFailed":false,"type":"TEST_STEP","name":"back","message":"Navigate back successfully","description":"","startTime":1522025812470,"endTime":1522025812510,"childRecords":[{"testStatus":{"stackTrace":"","statusValue":"PASSED"},"type":"MESSAGE","name":"","message":"Navigate back successfully","startTime":1522025812510,"endTime":0,"childRecords":[],"interuppted":false}],"interuppted":false},{"index":1,"isIgnoredIfFailed":false,"type":"TEST_STEP","name":"Statement - testString \u003d \"\" + index","description":"","startTime":1522025812510,"endTime":1522025812510,"childRecords":[],"interuppted":false},{"index":2,"isIgnoredIfFailed":false,"type":"TEST_STEP","name":"Statement - outputString \u003d \"Fibonacci of \" + index + \" is 1!\"","description":"","startTime":1522025812510,"endTime":1522025812510,"childRecords":[],"interuppted":false},{"index":3,"isIgnoredIfFailed":false,"type":"TEST_STEP","name":"setText","message":"Text \u00271003\u0027 is set on object \u0027Object Repository/GUI elements/Text element\u0027","description":"Use looping index as input","startTime":1522025812511,"endTime":1522025812606,"childRecords":[{"testStatus":{"stackTrace":"","statusValue":"PASSED"},"type":"MESSAGE","name":"","message":"Text \u00271003\u0027 is set on object \u0027Object Repository/GUI elements/Text element\u0027","startTime":1522025812606,"endTime":0,"childRecords":[],"interuppted":false}],"interuppted":false},{"index":4,"isIgnoredIfFailed":false,"type":"TEST_STEP","name":"click","message":"Object: \u0027Object Repository/GUI elements/Submit button\u0027 is clicked on","description":"Click on Submit","startTime":1522025812606,"endTime":1522025812791,"childRecords":[{"testStatus":{"stackTrace":"","statusValue":"PASSED"},"type":"MESSAGE","name":"","message":"Object: \u0027Object Repository/GUI elements/Submit button\u0027 is clicked on","startTime":1522025812791,"endTime":0,"childRecords":[],"interuppted":false}],"interuppted":false},{"index":5,"isIgnoredIfFailed":false,"type":"TEST_STEP","name":"verifyElementText","message":"Actual text and expected text of test object \u0027Object Repository/GUI elements/Div jumbotron\u0027 are matched.","description":"Compare output with expected value","startTime":1522025812792,"endTime":1522025812871,"childRecords":[{"testStatus":{"stackTrace":"","statusValue":"PASSED"},"type":"MESSAGE","name":"","message":"Actual text and expected text of test object \u0027Object Repository/GUI elements/Div jumbotron\u0027 are matched.","startTime":1522025812870,"endTime":0,"childRecords":[],"interuppted":false}],"interuppted":false},{"index":6,"isIgnoredIfFailed":false,"type":"TEST_STEP","name":"back","message":"Navigate back successfully","description":"","startTime":1522025812871,"endTime":1522025812967,"childRecords":[{"testStatus":{"stackTrace":"","statusValue":"PASSED"},"type":"MESSAGE","name":"","message":"Navigate back successfully","startTime":1522025812966,"endTime":0,"childRecords":[],"interuppted":false}],"interuppted":false},{"index":1,"isIgnoredIfFailed":false,"type":"TEST_STEP","name":"Statement - testString \u003d \"\" + index","description":"","startTime":1522025812968,"endTime":1522025812968,"childRecords":[],"interuppted":false},{"index":2,"isIgnoredIfFailed":false,"type":"TEST_STEP","name":"Statement - outputString \u003d \"Fibonacci of \" + index + \" is 1!\"","description":"","startTime":1522025812968,"endTime":1522025812968,"childRecords":[],"interuppted":false},{"index":3,"isIgnoredIfFailed":false,"type":"TEST_STEP","name":"setText","message":"Text \u00271004\u0027 is set on object \u0027Object Repository/GUI elements/Text element\u0027","description":"Use looping index as input","startTime":1522025812969,"endTime":1522025813094,"childRecords":[{"testStatus":{"stackTrace":"","statusValue":"PASSED"},"type":"MESSAGE","name":"","message":"Text \u00271004\u0027 is set on object \u0027Object Repository/GUI elements/Text element\u0027","startTime":1522025813093,"endTime":0,"childRecords":[],"interuppted":false}],"interuppted":false},{"index":4,"isIgnoredIfFailed":false,"type":"TEST_STEP","name":"click","message":"Object: \u0027Object Repository/GUI elements/Submit button\u0027 is clicked on","description":"Click on Submit","startTime":1522025813094,"endTime":1522025813325,"childRecords":[{"testStatus":{"stackTrace":"","statusValue":"PASSED"},"type":"MESSAGE","name":"","message":"Object: \u0027Object Repository/GUI elements/Submit button\u0027 is clicked on","startTime":1522025813324,"endTime":0,"childRecords":[],"interuppted":false}],"interuppted":false},{"index":5,"isIgnoredIfFailed":false,"type":"TEST_STEP","name":"verifyElementText","message":"Actual text and expected text of test object \u0027Object Repository/GUI elements/Div jumbotron\u0027 are matched.","description":"Compare output with expected value","startTime":1522025813325,"endTime":1522025813419,"childRecords":[{"testStatus":{"stackTrace":"","statusValue":"PASSED"},"type":"MESSAGE","name":"","message":"Actual text and expected text of test object \u0027Object Repository/GUI elements/Div jumbotron\u0027 are matched.","startTime":1522025813418,"endTime":0,"childRecords":[],"interuppted":false}],"interuppted":false},{"index":6,"isIgnoredIfFailed":false,"type":"TEST_STEP","name":"back","message":"Navigate back successfully","description":"","startTime":1522025813419,"endTime":1522025813486,"childRecords":[{"testStatus":{"stackTrace":"","statusValue":"PASSED"},"type":"MESSAGE","name":"","message":"Navigate back successfully","startTime":1522025813485,"endTime":0,"childRecords":[],"interuppted":false}],"interuppted":false},{"index":1,"isIgnoredIfFailed":false,"type":"TEST_STEP","name":"Statement - testString \u003d \"\" + index","description":"","startTime":1522025813486,"endTime":1522025813486,"childRecords":[],"interuppted":false},{"index":2,"isIgnoredIfFailed":false,"type":"TEST_STEP","name":"Statement - outputString \u003d \"Fibonacci of \" + index + \" is 1!\"","description":"","startTime":1522025813486,"endTime":1522025813486,"childRecords":[],"interuppted":false},{"index":3,"isIgnoredIfFailed":false,"type":"TEST_STEP","name":"setText","message":"Text \u00271005\u0027 is set on object \u0027Object Repository/GUI elements/Text element\u0027","description":"Use looping index as input","startTime":1522025813487,"endTime":1522025813651,"childRecords":[{"testStatus":{"stackTrace":"","statusValue":"PASSED"},"type":"MESSAGE","name":"","message":"Text \u00271005\u0027 is set on object \u0027Object Repository/GUI elements/Text element\u0027","startTime":1522025813650,"endTime":0,"childRecords":[],"interuppted":false}],"interuppted":false},{"index":4,"isIgnoredIfFailed":false,"type":"TEST_STEP","name":"click","message":"Object: \u0027Object Repository/GUI elements/Submit button\u0027 is clicked on","description":"Click on Submit","startTime":1522025813651,"endTime":1522025813840,"childRecords":[{"testStatus":{"stackTrace":"","statusValue":"PASSED"},"type":"MESSAGE","name":"","message":"Object: \u0027Object Repository/GUI elements/Submit button\u0027 is clicked on","startTime":1522025813839,"endTime":0,"childRecords":[],"interuppted":false}],"interuppted":false},{"index":5,"isIgnoredIfFailed":false,"type":"TEST_STEP","name":"verifyElementText","message":"Actual text and expected text of test object \u0027Object Repository/GUI elements/Div jumbotron\u0027 are matched.","description":"Compare output with expected value","startTime":1522025813840,"endTime":1522025813901,"childRecords":[{"testStatus":{"stackTrace":"","statusValue":"PASSED"},"type":"MESSAGE","name":"","message":"Actual text and expected text of test object \u0027Object Repository/GUI elements/Div jumbotron\u0027 are matched.","startTime":1522025813901,"endTime":0,"childRecords":[],"interuppted":false}],"interuppted":false},{"index":6,"isIgnoredIfFailed":false,"type":"TEST_STEP","name":"back","message":"Navigate back successfully","description":"","startTime":1522025813902,"endTime":1522025813983,"childRecords":[{"testStatus":{"stackTrace":"","statusValue":"PASSED"},"type":"MESSAGE","name":"","message":"Navigate back successfully","startTime":1522025813982,"endTime":0,"childRecords":[],"interuppted":false}],"interuppted":false},{"index":1,"isIgnoredIfFailed":false,"type":"TEST_STEP","name":"Statement - testString \u003d \"\" + index","description":"","startTime":1522025813983,"endTime":1522025813983,"childRecords":[],"interuppted":false},{"index":2,"isIgnoredIfFailed":false,"type":"TEST_STEP","name":"Statement - outputString \u003d \"Fibonacci of \" + index + \" is 1!\"","description":"","startTime":1522025813983,"endTime":1522025813984,"childRecords":[],"interuppted":false},{"index":3,"isIgnoredIfFailed":false,"type":"TEST_STEP","name":"setText","message":"Text \u00271006\u0027 is set on object \u0027Object Repository/GUI elements/Text element\u0027","description":"Use looping index as input","startTime":1522025813984,"endTime":1522025814119,"childRecords":[{"testStatus":{"stackTrace":"","statusValue":"PASSED"},"type":"MESSAGE","name":"","message":"Text \u00271006\u0027 is set on object \u0027Object Repository/GUI elements/Text element\u0027","startTime":1522025814119,"endTime":0,"childRecords":[],"interuppted":false}],"interuppted":false},{"index":4,"isIgnoredIfFailed":false,"type":"TEST_STEP","name":"click","message":"Object: \u0027Object Repository/GUI elements/Submit button\u0027 is clicked on","description":"Click on Submit","startTime":1522025814119,"endTime":1522025814310,"childRecords":[{"testStatus":{"stackTrace":"","statusValue":"PASSED"},"type":"MESSAGE","name":"","message":"Object: \u0027Object Repository/GUI elements/Submit button\u0027 is clicked on","startTime":1522025814309,"endTime":0,"childRecords":[],"interuppted":false}],"interuppted":false},{"index":5,"isIgnoredIfFailed":false,"type":"TEST_STEP","name":"verifyElementText","message":"Actual text and expected text of test object \u0027Object Repository/GUI elements/Div jumbotron\u0027 are matched.","description":"Compare output with expected value","startTime":1522025814310,"endTime":1522025814374,"childRecords":[{"testStatus":{"stackTrace":"","statusValue":"PASSED"},"type":"MESSAGE","name":"","message":"Actual text and expected text of test object \u0027Object Repository/GUI elements/Div jumbotron\u0027 are matched.","startTime":1522025814374,"endTime":0,"childRecords":[],"interuppted":false}],"interuppted":false},{"index":6,"isIgnoredIfFailed":false,"type":"TEST_STEP","name":"back","message":"Navigate back successfully","description":"","startTime":1522025814374,"endTime":1522025814446,"childRecords":[{"testStatus":{"stackTrace":"","statusValue":"PASSED"},"type":"MESSAGE","name":"","message":"Navigate back successfully","startTime":1522025814446,"endTime":0,"childRecords":[],"interuppted":false}],"interuppted":false},{"index":1,"isIgnoredIfFailed":false,"type":"TEST_STEP","name":"Statement - testString \u003d \"\" + index","description":"","startTime":1522025814446,"endTime":1522025814447,"childRecords":[],"interuppted":false},{"index":2,"isIgnoredIfFailed":false,"type":"TEST_STEP","name":"Statement - outputString \u003d \"Fibonacci of \" + index + \" is 1!\"","description":"","startTime":1522025814448,"endTime":1522025814448,"childRecords":[],"interuppted":false},{"index":3,"isIgnoredIfFailed":false,"type":"TEST_STEP","name":"setText","message":"Text \u00271007\u0027 is set on object \u0027Object Repository/GUI elements/Text element\u0027","description":"Use looping index as input","startTime":1522025814450,"endTime":1522025814576,"childRecords":[{"testStatus":{"stackTrace":"","statusValue":"PASSED"},"type":"MESSAGE","name":"","message":"Text \u00271007\u0027 is set on object \u0027Object Repository/GUI elements/Text element\u0027","startTime":1522025814575,"endTime":0,"childRecords":[],"interuppted":false}],"interuppted":false},{"index":4,"isIgnoredIfFailed":false,"type":"TEST_STEP","name":"click","message":"Object: \u0027Object Repository/GUI elements/Submit button\u0027 is clicked on","description":"Click on Submit","startTime":1522025814576,"endTime":1522025814698,"childRecords":[{"testStatus":{"stackTrace":"","statusValue":"PASSED"},"type":"MESSAGE","name":"","message":"Object: \u0027Object Repository/GUI elements/Submit button\u0027 is clicked on","startTime":1522025814697,"endTime":0,"childRecords":[],"interuppted":false}],"interuppted":false},{"index":5,"isIgnoredIfFailed":false,"type":"TEST_STEP","name":"verifyElementText","message":"Actual text and expected text of test object \u0027Object Repository/GUI elements/Div jumbotron\u0027 are matched.","description":"Compare output with expected value","startTime":1522025814698,"endTime":1522025814733,"childRecords":[{"testStatus":{"stackTrace":"","statusValue":"PASSED"},"type":"MESSAGE","name":"","message":"Actual text and expected text of test object \u0027Object Repository/GUI elements/Div jumbotron\u0027 are matched.","startTime":1522025814733,"endTime":0,"childRecords":[],"interuppted":false}],"interuppted":false},{"index":6,"isIgnoredIfFailed":false,"type":"TEST_STEP","name":"back","message":"Navigate back successfully","description":"","startTime":1522025814733,"endTime":1522025814779,"childRecords":[{"testStatus":{"stackTrace":"","statusValue":"PASSED"},"type":"MESSAGE","name":"","message":"Navigate back successfully","startTime":1522025814778,"endTime":0,"childRecords":[],"interuppted":false}],"interuppted":false},{"index":1,"isIgnoredIfFailed":false,"type":"TEST_STEP","name":"Statement - testString \u003d \"\" + index","description":"","startTime":1522025814779,"endTime":1522025814779,"childRecords":[],"interuppted":false},{"index":2,"isIgnoredIfFailed":false,"type":"TEST_STEP","name":"Statement - outputString \u003d \"Fibonacci of \" + index + \" is 1!\"","description":"","startTime":1522025814779,"endTime":1522025814779,"childRecords":[],"interuppted":false},{"index":3,"isIgnoredIfFailed":false,"type":"TEST_STEP","name":"setText","message":"Text \u00271008\u0027 is set on object \u0027Object Repository/GUI elements/Text element\u0027","description":"Use looping index as input","startTime":1522025814779,"endTime":1522025814888,"childRecords":[{"testStatus":{"stackTrace":"","statusValue":"PASSED"},"type":"MESSAGE","name":"","message":"Text \u00271008\u0027 is set on object \u0027Object Repository/GUI elements/Text element\u0027","startTime":1522025814888,"endTime":0,"childRecords":[],"interuppted":false}],"interuppted":false},{"index":4,"isIgnoredIfFailed":false,"type":"TEST_STEP","name":"click","message":"Object: \u0027Object Repository/GUI elements/Submit button\u0027 is clicked on","description":"Click on Submit","startTime":1522025814888,"endTime":1522025815018,"childRecords":[{"testStatus":{"stackTrace":"","statusValue":"PASSED"},"type":"MESSAGE","name":"","message":"Object: \u0027Object Repository/GUI elements/Submit button\u0027 is clicked on","startTime":1522025815017,"endTime":0,"childRecords":[],"interuppted":false}],"interuppted":false},{"index":5,"isIgnoredIfFailed":false,"type":"TEST_STEP","name":"verifyElementText","message":"Actual text and expected text of test object \u0027Object Repository/GUI elements/Div jumbotron\u0027 are matched.","description":"Compare output with expected value","startTime":1522025815018,"endTime":1522025815054,"childRecords":[{"testStatus":{"stackTrace":"","statusValue":"PASSED"},"type":"MESSAGE","name":"","message":"Actual text and expected text of test object \u0027Object Repository/GUI elements/Div jumbotron\u0027 are matched.","startTime":1522025815054,"endTime":0,"childRecords":[],"interuppted":false}],"interuppted":false},{"index":6,"isIgnoredIfFailed":false,"type":"TEST_STEP","name":"back","message":"Navigate back successfully","description":"","startTime":1522025815054,"endTime":1522025815092,"childRecords":[{"testStatus":{"stackTrace":"","statusValue":"PASSED"},"type":"MESSAGE","name":"","message":"Navigate back successfully","startTime":1522025815091,"endTime":0,"childRecords":[],"interuppted":false}],"interuppted":false},{"index":1,"isIgnoredIfFailed":false,"type":"TEST_STEP","name":"Statement - testString \u003d \"\" + index","description":"","startTime":1522025815092,"endTime":1522025815092,"childRecords":[],"interuppted":false},{"index":2,"isIgnoredIfFailed":false,"type":"TEST_STEP","name":"Statement - outputString \u003d \"Fibonacci of \" + index + \" is 1!\"","description":"","startTime":1522025815092,"endTime":1522025815092,"childRecords":[],"interuppted":false},{"index":3,"isIgnoredIfFailed":false,"type":"TEST_STEP","name":"setText","message":"Text \u00271009\u0027 is set on object \u0027Object Repository/GUI elements/Text element\u0027","description":"Use looping index as input","startTime":1522025815092,"endTime":1522025815189,"childRecords":[{"testStatus":{"stackTrace":"","statusValue":"PASSED"},"type":"MESSAGE","name":"","message":"Text \u00271009\u0027 is set on object \u0027Object Repository/GUI elements/Text element\u0027","startTime":1522025815188,"endTime":0,"childRecords":[],"interuppted":false}],"interuppted":false},{"index":4,"isIgnoredIfFailed":false,"type":"TEST_STEP","name":"click","message":"Object: \u0027Object Repository/GUI elements/Submit button\u0027 is clicked on","description":"Click on Submit","startTime":1522025815189,"endTime":1522025815344,"childRecords":[{"testStatus":{"stackTrace":"","statusValue":"PASSED"},"type":"MESSAGE","name":"","message":"Object: \u0027Object Repository/GUI elements/Submit button\u0027 is clicked on","startTime":1522025815344,"endTime":0,"childRecords":[],"interuppted":false}],"interuppted":false},{"index":5,"isIgnoredIfFailed":false,"type":"TEST_STEP","name":"verifyElementText","message":"Actual text and expected text of test object \u0027Object Repository/GUI elements/Div jumbotron\u0027 are matched.","description":"Compare output with expected value","startTime":1522025815344,"endTime":1522025815401,"childRecords":[{"testStatus":{"stackTrace":"","statusValue":"PASSED"},"type":"MESSAGE","name":"","message":"Actual text and expected text of test object \u0027Object Repository/GUI elements/Div jumbotron\u0027 are matched.","startTime":1522025815400,"endTime":0,"childRecords":[],"interuppted":false}],"interuppted":false},{"index":6,"isIgnoredIfFailed":false,"type":"TEST_STEP","name":"back","message":"Navigate back successfully","description":"","startTime":1522025815401,"endTime":1522025815498,"childRecords":[{"testStatus":{"stackTrace":"","statusValue":"PASSED"},"type":"MESSAGE","name":"","message":"Navigate back successfully","startTime":1522025815497,"endTime":0,"childRecords":[],"interuppted":false}],"interuppted":false},{"index":1,"isIgnoredIfFailed":false,"type":"TEST_STEP","name":"Statement - testString \u003d \"\" + index","description":"","startTime":1522025815498,"endTime":1522025815499,"childRecords":[],"interuppted":false},{"index":2,"isIgnoredIfFailed":false,"type":"TEST_STEP","name":"Statement - outputString \u003d \"Fibonacci of \" + index + \" is 1!\"","description":"","startTime":1522025815500,"endTime":1522025815500,"childRecords":[],"interuppted":false},{"index":3,"isIgnoredIfFailed":false,"type":"TEST_STEP","name":"setText","message":"Text \u00271010\u0027 is set on object \u0027Object Repository/GUI elements/Text element\u0027","description":"Use looping index as input","startTime":1522025815501,"endTime":1522025815669,"childRecords":[{"testStatus":{"stackTrace":"","statusValue":"PASSED"},"type":"MESSAGE","name":"","message":"Text \u00271010\u0027 is set on object \u0027Object Repository/GUI elements/Text element\u0027","startTime":1522025815668,"endTime":0,"childRecords":[],"interuppted":false}],"interuppted":false},{"index":4,"isIgnoredIfFailed":false,"type":"TEST_STEP","name":"click","message":"Object: \u0027Object Repository/GUI elements/Submit button\u0027 is clicked on","description":"Click on Submit","startTime":1522025815669,"endTime":1522025815800,"childRecords":[{"testStatus":{"stackTrace":"","statusValue":"PASSED"},"type":"MESSAGE","name":"","message":"Object: \u0027Object Repository/GUI elements/Submit button\u0027 is clicked on","startTime":1522025815799,"endTime":0,"childRecords":[],"interuppted":false}],"interuppted":false},{"index":5,"isIgnoredIfFailed":false,"type":"TEST_STEP","name":"verifyElementText","message":"Actual text and expected text of test object \u0027Object Repository/GUI elements/Div jumbotron\u0027 are matched.","description":"Compare output with expected value","startTime":1522025815800,"endTime":1522025815847,"childRecords":[{"testStatus":{"stackTrace":"","statusValue":"PASSED"},"type":"MESSAGE","name":"","message":"Actual text and expected text of test object \u0027Object Repository/GUI elements/Div jumbotron\u0027 are matched.","startTime":1522025815846,"endTime":0,"childRecords":[],"interuppted":false}],"interuppted":false},{"index":6,"isIgnoredIfFailed":false,"type":"TEST_STEP","name":"back","message":"Navigate back successfully","description":"","startTime":1522025815847,"endTime":1522025815935,"childRecords":[{"testStatus":{"stackTrace":"","statusValue":"PASSED"},"type":"MESSAGE","name":"","message":"Navigate back successfully","startTime":1522025815934,"endTime":0,"childRecords":[],"interuppted":false}],"interuppted":false}],"interuppted":false},{"index":5,"isIgnoredIfFailed":false,"type":"TEST_STEP","name":"closeBrowser","message":"Browser is closed","description":"","startTime":1522025815935,"endTime":1522025816554,"childRecords":[{"testStatus":{"stackTrace":"","statusValue":"PASSED"},"type":"MESSAGE","name":"","message":"Browser is closed","startTime":1522025816553,"endTime":0,"childRecords":[],"interuppted":false}],"interuppted":false},{"testStatus":{"stackTrace":"","statusValue":"PASSED"},"type":"MESSAGE","name":"","message":"Test Cases/Fibonacci Page/Fibonacci - Corner","startTime":1522025816554,"endTime":0,"childRecords":[],"interuppted":false}],"interuppted":false}],"interuppted":false}